LICENSE.txt
README.md
setup.cfg
setup.py
whatajoke/__init__.py
whatajoke/service.py
whatajoke/whatajoke.py
whatajoke.egg-info/PKG-INFO
whatajoke.egg-info/SOURCES.txt
whatajoke.egg-info/dependency_links.txt
whatajoke.egg-info/entry_points.txt
whatajoke.egg-info/requires.txt
whatajoke.egg-info/top_level.txt
whatajoke/commands/__init__.py
whatajoke/commands/login.py
whatajoke/commands/send.py
whatajoke/joke/__init__.py
whatajoke/joke/joke_formatter.py
whatajoke/joke/joke_service.py
whatajoke/joke/url_helper.py
whatajoke/whatsapp/__init__.py
whatajoke/whatsapp/whatsapp_service.py