Metadata-Version: 2.1
Name: whatajoke
Version: 1.1.11
Summary: Send a joke to a Whatsapp group!
Home-page: https://github.com/joaoduartepinto/whatajoke
Author: Joao Duarte Pinto
Author-email: joaoduartepinto@outlook.com
License: GPLv3
Download-URL: https://github.com/joaoduartepinto/whatajoke/archive/refs/tags/v1.1.11.tar.gz
Platform: UNKNOWN
License-File: LICENSE.txt
